visionflow/camera_client.py
visionflow/camera_server.py
visionflow/log_manager.py
visionflow-0.0.0.dist-info/METADATA
visionflow-0.0.0.dist-info/WHEEL
visionflow-0.0.0.dist-info/RECORD
