Metadata-Version: 2.1
Name: visionflow
Version: 0.0.0
Summary: manage multiple camera connections over a network
License: MIT
Author: Mac Prible
Author-email: prible@gmail.com
Requires-Python: >=3.10,<3.12
Classifier: License :: OSI Approved :: MIT License
Classifier: Programming Language :: Python :: 3
Classifier: Programming Language :: Python :: 3.10
Classifier: Programming Language :: Python :: 3.11
Requires-Dist: PySide6 (>=6.5.2,<7.0.0)
Requires-Dist: opencv-contrib-python (>=4.8.0.76,<5.0.0.0)
